cloudantic/__init__.py
cloudantic/router/__init__.py
cloudantic/router/api.py
cloudantic/router/docs.py
cloudantic/router/helpers.py
cloudantic/router/server.py
cloudantic/schema/__init__.py
cloudantic/schema/json.py
cloudantic/schema/odm.py
cloudantic/schema/schema.py
cloudantic/schema/streams.py
cloudantic/schema/typedef.py
cloudantic/services/__init__.py
cloudantic/services/apiclient.py
cloudantic/services/cognito.py
cloudantic/services/functions.py
cloudantic/services/kinesis.py
cloudantic/services/openai.py
cloudantic/services/storage.py
cloudantic/utils.py
cloudantic-0.0.8.dist-info/METADATA
cloudantic-0.0.8.dist-info/WHEEL
cloudantic-0.0.8.dist-info/RECORD
